Metadata-Version: 2.1
Name: pywhatsbomb
Version: 1.0
Summary: A powerful tool for WhatsApp prank
Home-page: https://github.com/Raguggg/pywhatsbomb
Author: Ragu G
Author-email: ragu19062002@gmail.com
License: MIT
Keywords: whatsapp,prank,bot,automation,spamming,mass messaging,flooding,joke
Classifier: Development Status :: 5 - Production/Stable
Classifier: Intended Audience :: Education
Classifier: Operating System :: Microsoft :: Windows :: Windows 10
Classifier: License :: OSI Approved :: MIT License
Classifier: Programming Language :: Python :: 3
License-File: LICENSE.txt
